README.txt
setup.py
evax/__init__.py
evax.bitten.tools.egg-info/PKG-INFO
evax.bitten.tools.egg-info/SOURCES.txt
evax.bitten.tools.egg-info/dependency_links.txt
evax.bitten.tools.egg-info/entry_points.txt
evax.bitten.tools.egg-info/namespace_packages.txt
evax.bitten.tools.egg-info/not-zip-safe
evax.bitten.tools.egg-info/requires.txt
evax.bitten.tools.egg-info/top_level.txt
evax/bitten/__init__.py
evax/bitten/tools/__init__.py
evax/bitten/tools/check.py
evax/bitten/tools/lcov.py
evax/bitten/tools/tests.py