Metadata-Version: 1.0
Name: evax.bitten.tools
Version: 1.0
Summary: Bitten plugin adding check and lcov support
Home-page: http://www.evax.fr/open-source-software/evax.bitten.tools
Author: Evax Software
Author-email: contact@evax.fr
License: BSD
Keywords: trac,bitten,check,lcov
Platform: UNKNOWN
Classifier: Programming Language :: Python
Classifier: Development Status :: 5 - Production/Stable
Classifier: Environment :: Plugins
Classifier: Framework :: Trac
Classifier: Operating System :: OS Independent
Classifier: Intended Audience :: Developers
Classifier: License :: OSI Approved :: BSD License
Classifier: Topic :: Software Development :: Quality Assurance
Classifier: Topic :: Software Development :: Testing
